pyd_sqa/__init__.py
pyd_sqa/main.py
pyd_sqa-0.0.9.dist-info/LICENSE
pyd_sqa-0.0.9.dist-info/METADATA
pyd_sqa-0.0.9.dist-info/WHEEL
pyd_sqa-0.0.9.dist-info/RECORD
