Metadata-Version: 2.1
Name: pyd-sqa
Version: 0.0.9
Summary: Tools to convert SQLAlchemy models to Pydantic models, forked from tiangolo/pydantic-sqlalchemy
License: MIT
Author: Sebastian López
Author-email: selobu@gmail.com
Requires-Python: >=3.9,<4.0
Classifier: License :: OSI Approved :: MIT License
Classifier: Programming Language :: Python :: 3
Classifier: Programming Language :: Python :: 3.9
Classifier: Programming Language :: Python :: 3.10
Classifier: Programming Language :: Python :: 3.11
Provides-Extra: dev
Requires-Dist: autoflake[dev] (>=1.3.1,<2.0.0) ; extra == "dev"
Requires-Dist: flake8[dev] (>=3.7.9,<4.0.0) ; extra == "dev"
Requires-Dist: jupyter[dev] (>=1.0.0,<2.0.0) ; extra == "dev"
Requires-Dist: pydantic (>=2.0.3,<3.0.0)
Requires-Dist: sqlalchemy (==2.0.0)
